lavague/contexts/openai/__init__.py
lavague/contexts/openai/base.py
lavague_contexts_openai-0.2.3.dist-info/METADATA
lavague_contexts_openai-0.2.3.dist-info/WHEEL
lavague_contexts_openai-0.2.3.dist-info/RECORD
